aws/handler.py
aws/link_so.py
aws/mk_dist.py
aws/mk_dist.sh
docker/Dockerfile
docker/pydem_user_guide.md
docker/requirements.txt
pydem/CHANGELOG.md
pydem/__init__.py
pydem/commandline_utils.py
pydem/dem_processing.py
pydem/process_manager.py
pydem/utils.py
pydem/utils_test_pydem.py
pydem/cyfuncs/__init__.py
pydem/cyfuncs/cyutils.cpp
pydem/cyfuncs/cyutils.cpython-311-x86_64-linux-gnu.so
pydem/cyfuncs/cyutils.pyx
pydem/cyfuncs/cyutils.so
pydem/examples/process_array.py
pydem/examples/process_manager_directory.py
pydem/test/test_NN032_033_elev.tif
pydem/test/test_docker_container.py
pydem/test/test_end_to_end.py
pydem-1.2.0.dist-info/METADATA
pydem-1.2.0.dist-info/WHEEL
pydem-1.2.0.dist-info/entry_points.txt
pydem-1.2.0.dist-info/top_level.txt
pydem-1.2.0.dist-info/RECORD
pydem-1.2.0.dist-info/licenses/LICENSE.txt
