Metadata-Version: 2.4
Name: pyDEM
Version: 1.2.0
Summary: Software for calculating Topographic Wetness Index (TWI)
Author: Creare
License-Expression: Apache-2.0
Project-URL: Homepage, https://github.com/creare-com/pydem
Requires-Python: >=3
License-File: LICENSE.txt
Requires-Dist: rasterio
Requires-Dist: numpy
Requires-Dist: scipy
Requires-Dist: geopy
Requires-Dist: traitlets
Requires-Dist: traittypes
Requires-Dist: zarr
Requires-Dist: cython
Dynamic: license-file
